{
  "iso2": "US",
  "nameKo": "미국",
  "nameEn": "United States",
  "nameCn": "美国",
  "nameJp": "アメリカ合衆国",
  "power": {
    "plug": [
      "A",
      "B"
    ],
    "voltage": "120V",
    "frequency": "60Hz"
  },
  "airline": [
    "KE",
    "OZ",
    "YP",
    "UA",
    "DL",
    "AA",
    "HA"
  ],
  "baggage": {
    "links": [
      {
        "code": "KE",
        "name": "Korean Air",
        "url": "https://www.koreanair.com/kr/ko/airport/baggage"
      },
      {
        "code": "OZ",
        "name": "Asiana Airlines",
        "url": "https://flyasiana.com/C/KR/KO/contents/user-guide"
      },
      {
        "code": "YP",
        "name": "Air Premia",
        "url": "https://www.airpremia.com/kr/ko/support/baggage/free-baggage"
      },
      {
        "code": "UA",
        "name": "United",
        "url": "https://www.united.com/en/kr/fly/travel/baggage.html"
      },
      {
        "code": "DL",
        "name": "Delta",
        "url": "https://www.delta.com/us/en/baggage/overview"
      },
      {
        "code": "AA",
        "name": "American Airlines",
        "url": "https://www.aa.com/i18n/travel-info/baggage/checked-baggage.jsp"
      },
      {
        "code": "HA",
        "name": "Hawaiian",
        "url": "https://www.hawaiianairlines.com/ko-kr/travel-information/baggage"
      }
    ]
  },
  "updatedAt": "2025-08-21T15:47:19.135+09:00",
  "_note": "항공사/수하물 링크는 수시 변경 가능 — 운영 중 확인/보정 필요"
}